simplefix/__init__.py
simplefix/constants.py
simplefix/data.py
simplefix/errors.py
simplefix/message.py
simplefix/parser.py
simplefix-1.0.17.dist-info/LICENSE
simplefix-1.0.17.dist-info/METADATA
simplefix-1.0.17.dist-info/WHEEL
simplefix-1.0.17.dist-info/top_level.txt
simplefix-1.0.17.dist-info/RECORD
